<annotation>
	<folder>train</folder>
	<filename>0132 .jpg</filename>
	<path>C:\Users\Sharpel Malak\Downloads\allData\train\0132 .jpg</path>
	<source>
		<database>Unknown</database>
	</source>
	<size>
		<width>750</width>
		<height>750</height>
		<depth>3</depth>
	</size>
	<segmented>0</segmented>
	<object>
		<name>carpl</name>
		<pose>Unspecified</pose>
		<truncated>0</truncated>
		<difficult>0</difficult>
		<bndbox>
			<xmin>451</xmin>
			<ymin>505</ymin>
			<xmax>555</xmax>
			<ymax>562</ymax>
		</bndbox>
	</object>
</annotation>
